raiz/__init__.py
raiz/cli.py
raiz/commands.py
raiz/utils/__init__.py
raiz/utils/database.py
raiz/utils/db.py
raiz/utils/report_generator.py
raiz-0.1.1.dist-info/licenses/LICENSE
raiz-0.1.1.dist-info/METADATA
raiz-0.1.1.dist-info/WHEEL
raiz-0.1.1.dist-info/entry_points.txt
raiz-0.1.1.dist-info/top_level.txt
raiz-0.1.1.dist-info/RECORD
