Metadata-Version: 2.4
Name: raiz
Version: 0.1.1
Summary: Raiz - Simple CLI Requirements Management Tool
Author-email: daleonpz <daniel@baremetallics.com>
License-Expression: Apache-2.0
Project-URL: Homepage, https://github.com/daleonpz/raiz
Project-URL: Issues, https://github.com/daleonpz/raiz/issues
Classifier: Development Status :: 4 - Beta
Classifier: Intended Audience :: Developers
Classifier: Programming Language :: Python :: 3
Classifier: Programming Language :: Python :: 3.8
Classifier: Programming Language :: Python :: 3.9
Classifier: Programming Language :: Python :: 3.10
Classifier: Programming Language :: Python :: 3.11
Classifier: Topic :: Software Development :: Build Tools
Classifier: Topic :: Software Development :: Libraries :: Python Modules
Classifier: Topic :: Utilities
Classifier: Environment :: Console
Requires-Python: >=3.8
License-File: LICENSE
Requires-Dist: typer>=0.12.0
Requires-Dist: PyYAML>=6.0
Requires-Dist: rich>=13.0.0
Requires-Dist: robotframework>=7.0
Requires-Dist: robotframework-jsonlibrary>=0.4
Provides-Extra: dev
Requires-Dist: pytest>=8.0; extra == "dev"
Requires-Dist: black>=24.0; extra == "dev"
Requires-Dist: ruff>=0.7; extra == "dev"
Dynamic: license-file
